LICENSE
MANIFEST.in
README.md
setup.py
apimaticcalculatorpython/__init__.py
apimaticcalculatorpython/api_helper.py
apimaticcalculatorpython/apimaticcalculatorpython_client.py
apimaticcalculatorpython/configuration.py
apimaticcalculatorpython/decorators.py
apimaticcalculatorpython.egg-info/PKG-INFO
apimaticcalculatorpython.egg-info/SOURCES.txt
apimaticcalculatorpython.egg-info/dependency_links.txt
apimaticcalculatorpython.egg-info/requires.txt
apimaticcalculatorpython.egg-info/top_level.txt
apimaticcalculatorpython/controllers/__init__.py
apimaticcalculatorpython/controllers/base_controller.py
apimaticcalculatorpython/controllers/calculator_e_ps.py
apimaticcalculatorpython/exceptions/__init__.py
apimaticcalculatorpython/exceptions/api_exception.py
apimaticcalculatorpython/http/__init__.py
apimaticcalculatorpython/http/http_call_back.py
apimaticcalculatorpython/http/http_client.py
apimaticcalculatorpython/http/http_context.py
apimaticcalculatorpython/http/http_method_enum.py
apimaticcalculatorpython/http/http_request.py
apimaticcalculatorpython/http/http_response.py
apimaticcalculatorpython/http/requests_client.py
apimaticcalculatorpython/models/__init__.py
apimaticcalculatorpython/models/operation_type.py
tests/__init__.py
tests/http_response_catcher.py
tests/test_helper.py
tests/controllers/__init__.py
tests/controllers/controller_test_base.py
tests/controllers/test_calculator_e_ps.py