Metadata-Version: 1.0
Name: apimaticcalculatorpython
Version: 1.1.99263
Summary: Simple calculator API hosted on APIMATIC
Home-page: https://apimatic.io
Author: APIMatic SDK Generator
Author-email: support@apimatic.io
License: UNKNOWN
Platform: UNKNOWN
